[
    {
        "id": {
            "$oid": "6563e6c1fc13ae0d4c4cd382"
        },
        "username": "123",
        "password": "123",
        "email": "gfone0@bloglovin.com",
        "cellphone": "866-149-5123",
        "address": "6939 Longview Parkway",
        "birthday": "01/12/2023",
        "contacts": [
            {
                "$oid": "6563e6c1fc13ae0d4c4cd383"
            },
            {
                "$oid": "6563e6c1fc13ae0d4c4cd384"
            },
            {
                "$oid": "6563e6c1fc13ae0d4c4cd385"
            },
            {
                "$oid": "6563e6c1fc13ae0d4c4cd386"
            },
            {
                "$oid": "6563e6c1fc13ae0d4c4cd387"
            }
        ]
    },
    {
        "id": {
            "$oid": "6563e6c1fc13ae0d4c4cd388"
        },
        "username": "Junie Giorgioni",
        "password": "rZ1<S\\lA9v'2LGd?",
        "email": "jgiorgioni1@npr.org",
        "cellphone": "200-609-8296",
        "address": "36086 Bowman Junction",
        "birthday": "10/10/2023",
        "contacts": [
            {
                "$oid": "6563e6c1fc13ae0d4c4cd389"
            },
            {
                "$oid": "6563e6c1fc13ae0d4c4cd38a"
            },
            {
                "$oid": "6563e6c1fc13ae0d4c4cd38b"
            },
            {
                "$oid": "6563e6c1fc13ae0d4c4cd38c"
            },
            {
                "$oid": "6563e6c1fc13ae0d4c4cd38d"
            }
        ]
    },
    {
        "id": {
            "$oid": "6563e6c1fc13ae0d4c4cd38e"
        },
        "username": "Hesther Whitmore",
        "password": "yP7)b~'OFs=Wk)9",
        "email": "hwhitmore2@usda.gov",
        "cellphone": "177-211-7541",
        "address": "0 Prentice Place",
        "birthday": "10/22/2023",
        "contacts": [
            {
                "$oid": "6563e6c1fc13ae0d4c4cd38f"
            },
            {
                "$oid": "6563e6c1fc13ae0d4c4cd390"
            },
            {
                "$oid": "6563e6c1fc13ae0d4c4cd391"
            },
            {
                "$oid": "6563e6c1fc13ae0d4c4cd392"
            },
            {
                "$oid": "6563e6c1fc13ae0d4c4cd393"
            }
        ]
    },
    {
        "id": {
            "$oid": "6563e6c1fc13ae0d4c4cd394"
        },
        "username": "Graham Connor",
        "password": "fK7%wu#>Ev",
        "email": "gconnor3@cyberchimps.com",
        "cellphone": "405-118-3164",
        "address": "11 Meadow Valley Junction",
        "birthday": "11/02/2023",
        "contacts": [
            {
                "$oid": "6563e6c1fc13ae0d4c4cd395"
            },
            {
                "$oid": "6563e6c1fc13ae0d4c4cd396"
            },
            {
                "$oid": "6563e6c1fc13ae0d4c4cd397"
            },
            {
                "$oid": "6563e6c1fc13ae0d4c4cd398"
            },
            {
                "$oid": "6563e6c1fc13ae0d4c4cd399"
            }
        ]
    },
    {
        "id": {
            "$oid": "6563e6c1fc13ae0d4c4cd39a"
        },
        "username": "Althea Vallack",
        "password": "jL3@@h?Mn_",
        "email": "avallack4@microsoft.com",
        "cellphone": "701-629-2908",
        "address": "6 Westport Place",
        "birthday": "12/28/2022",
        "contacts": [
            {
                "$oid": "6563e6c1fc13ae0d4c4cd39b"
            },
            {
                "$oid": "6563e6c1fc13ae0d4c4cd39c"
            },
            {
                "$oid": "6563e6c1fc13ae0d4c4cd39d"
            },
            {
                "$oid": "6563e6c1fc13ae0d4c4cd39e"
            },
            {
                "$oid": "6563e6c1fc13ae0d4c4cd39f"
            }
        ]
    },
    {
        "id": {
            "$oid": "6563e6c1fc13ae0d4c4cd3a0"
        },
        "username": "Perri Autin",
        "password": "tR7/*g/hzH67n",
        "email": "pautin5@earthlink.net",
        "cellphone": "796-966-2579",
        "address": "05405 Sunfield Trail",
        "birthday": "09/28/2023",
        "contacts": [
            {
                "$oid": "6563e6c1fc13ae0d4c4cd3a1"
            },
            {
                "$oid": "6563e6c1fc13ae0d4c4cd3a2"
            },
            {
                "$oid": "6563e6c1fc13ae0d4c4cd3a3"
            },
            {
                "$oid": "6563e6c1fc13ae0d4c4cd3a4"
            },
            {
                "$oid": "6563e6c1fc13ae0d4c4cd3a5"
            }
        ]
    },
    {
        "id": {
            "$oid": "6563e6c1fc13ae0d4c4cd3a6"
        },
        "username": "Kylie Malkin",
        "password": "eW4.}}Z=HeRrz.`",
        "email": "kmalkin6@ask.com",
        "cellphone": "454-539-8809",
        "address": "1249 Village Lane",
        "birthday": "10/08/2023",
        "contacts": [
            {
                "$oid": "6563e6c1fc13ae0d4c4cd3a7"
            },
            {
                "$oid": "6563e6c1fc13ae0d4c4cd3a8"
            },
            {
                "$oid": "6563e6c1fc13ae0d4c4cd3a9"
            },
            {
                "$oid": "6563e6c1fc13ae0d4c4cd3aa"
            },
            {
                "$oid": "6563e6c1fc13ae0d4c4cd3ab"
            }
        ]
    },
    {
        "id": {
            "$oid": "6563e6c1fc13ae0d4c4cd3ac"
        },
        "username": "Sherrie Dulinty",
        "password": "bI7}E45grQi7W*H",
        "email": "sdulinty7@ovh.net",
        "cellphone": "931-180-2941",
        "address": "46137 Oak Avenue",
        "birthday": "12/24/2022",
        "contacts": [
            {
                "$oid": "6563e6c1fc13ae0d4c4cd3ad"
            },
            {
                "$oid": "6563e6c1fc13ae0d4c4cd3ae"
            },
            {
                "$oid": "6563e6c1fc13ae0d4c4cd3af"
            },
            {
                "$oid": "6563e6c1fc13ae0d4c4cd3b0"
            },
            {
                "$oid": "6563e6c1fc13ae0d4c4cd3b1"
            }
        ]
    },
    {
        "id": {
            "$oid": "6563e6c1fc13ae0d4c4cd3b2"
        },
        "username": "Fleur Scotchford",
        "password": "aF5{10~2.7fur&e",
        "email": "fscotchford8@qq.com",
        "cellphone": "677-423-9196",
        "address": "191 Commercial Parkway",
        "birthday": "03/09/2023",
        "contacts": [
            {
                "$oid": "6563e6c1fc13ae0d4c4cd3b3"
            },
            {
                "$oid": "6563e6c1fc13ae0d4c4cd3b4"
            },
            {
                "$oid": "6563e6c1fc13ae0d4c4cd3b5"
            },
            {
                "$oid": "6563e6c1fc13ae0d4c4cd3b6"
            },
            {
                "$oid": "6563e6c1fc13ae0d4c4cd3b7"
            }
        ]
    },
    {
        "id": {
            "$oid": "6563e6c1fc13ae0d4c4cd3b8"
        },
        "username": "Carmita Heggman",
        "password": "sE6\\L11)'Z",
        "email": "cheggman9@cdbaby.com",
        "cellphone": "108-326-0879",
        "address": "9 Anhalt Way",
        "birthday": "11/02/2023",
        "contacts": [
            {
                "$oid": "6563e6c1fc13ae0d4c4cd3b9"
            },
            {
                "$oid": "6563e6c1fc13ae0d4c4cd3ba"
            },
            {
                "$oid": "6563e6c1fc13ae0d4c4cd3bb"
            },
            {
                "$oid": "6563e6c1fc13ae0d4c4cd3bc"
            },
            {
                "$oid": "6563e6c1fc13ae0d4c4cd3bd"
            }
        ]
    },
    {
        "id": {
            "$oid": "6563e6c1fc13ae0d4c4cd3be"
        },
        "username": "Jeannine Flood",
        "password": "vV3_~0Yc/q",
        "email": "jflooda@liveinternet.ru",
        "cellphone": "514-368-6868",
        "address": "4270 Hanover Way",
        "birthday": "12/06/2022",
        "contacts": [
            {
                "$oid": "6563e6c1fc13ae0d4c4cd3bf"
            },
            {
                "$oid": "6563e6c1fc13ae0d4c4cd3c0"
            },
            {
                "$oid": "6563e6c1fc13ae0d4c4cd3c1"
            },
            {
                "$oid": "6563e6c1fc13ae0d4c4cd3c2"
            },
            {
                "$oid": "6563e6c1fc13ae0d4c4cd3c3"
            }
        ]
    },
    {
        "id": {
            "$oid": "6563e6c1fc13ae0d4c4cd3c4"
        },
        "username": "Isidoro Smythin",
        "password": "dY9%CqpRT\\jy",
        "email": "ismythinb@amazon.com",
        "cellphone": "854-172-9405",
        "address": "81926 Hooker Plaza",
        "birthday": "01/24/2023",
        "contacts": [
            {
                "$oid": "6563e6c1fc13ae0d4c4cd3c5"
            },
            {
                "$oid": "6563e6c1fc13ae0d4c4cd3c6"
            },
            {
                "$oid": "6563e6c1fc13ae0d4c4cd3c7"
            },
            {
                "$oid": "6563e6c1fc13ae0d4c4cd3c8"
            },
            {
                "$oid": "6563e6c1fc13ae0d4c4cd3c9"
            }
        ]
    },
    {
        "id": {
            "$oid": "6563e6c1fc13ae0d4c4cd3ca"
        },
        "username": "Leonid Coviello",
        "password": "bN8*TJD*=}KGoT'd",
        "email": "lcovielloc@networkadvertising.org",
        "cellphone": "629-501-6294",
        "address": "9193 American Avenue",
        "birthday": "12/14/2022",
        "contacts": [
            {
                "$oid": "6563e6c1fc13ae0d4c4cd3cb"
            },
            {
                "$oid": "6563e6c1fc13ae0d4c4cd3cc"
            },
            {
                "$oid": "6563e6c1fc13ae0d4c4cd3cd"
            },
            {
                "$oid": "6563e6c1fc13ae0d4c4cd3ce"
            },
            {
                "$oid": "6563e6c1fc13ae0d4c4cd3cf"
            }
        ]
    },
    {
        "id": {
            "$oid": "6563e6c1fc13ae0d4c4cd3d0"
        },
        "username": "Jerrilyn McClintock",
        "password": "bB4.&d/r{!",
        "email": "jmcclintockd@example.com",
        "cellphone": "294-655-1626",
        "address": "387 Mcguire Place",
        "birthday": "10/10/2023",
        "contacts": [
            {
                "$oid": "6563e6c1fc13ae0d4c4cd3d1"
            },
            {
                "$oid": "6563e6c1fc13ae0d4c4cd3d2"
            },
            {
                "$oid": "6563e6c1fc13ae0d4c4cd3d3"
            },
            {
                "$oid": "6563e6c1fc13ae0d4c4cd3d4"
            },
            {
                "$oid": "6563e6c1fc13ae0d4c4cd3d5"
            }
        ]
    },
    {
        "id": {
            "$oid": "6563e6c1fc13ae0d4c4cd3d6"
        },
        "username": "Natividad D'Agostini",
        "password": "dT9%YvzF)Ic2t}",
        "email": "ndagostinie@elegantthemes.com",
        "cellphone": "949-480-9615",
        "address": "194 Oak Plaza",
        "birthday": "10/01/2023",
        "contacts": [
            {
                "$oid": "6563e6c1fc13ae0d4c4cd3d7"
            },
            {
                "$oid": "6563e6c1fc13ae0d4c4cd3d8"
            },
            {
                "$oid": "6563e6c1fc13ae0d4c4cd3d9"
            },
            {
                "$oid": "6563e6c1fc13ae0d4c4cd3da"
            },
            {
                "$oid": "6563e6c1fc13ae0d4c4cd3db"
            }
        ]
    },
    {
        "id": {
            "$oid": "6563e6c1fc13ae0d4c4cd3dc"
        },
        "username": "Latrina Alderson",
        "password": "dV2{{kDhEwsD",
        "email": "laldersonf@feedburner.com",
        "cellphone": "761-651-8393",
        "address": "45955 Pond Avenue",
        "birthday": "05/28/2023",
        "contacts": [
            {
                "$oid": "6563e6c1fc13ae0d4c4cd3dd"
            },
            {
                "$oid": "6563e6c1fc13ae0d4c4cd3de"
            },
            {
                "$oid": "6563e6c1fc13ae0d4c4cd3df"
            },
            {
                "$oid": "6563e6c1fc13ae0d4c4cd3e0"
            },
            {
                "$oid": "6563e6c1fc13ae0d4c4cd3e1"
            }
        ]
    },
    {
        "id": {
            "$oid": "6563e6c1fc13ae0d4c4cd3e2"
        },
        "username": "Rupert Easun",
        "password": "tP1(EP/2\"",
        "email": "reasung@hc360.com",
        "cellphone": "511-599-0140",
        "address": "201 Dexter Plaza",
        "birthday": "09/14/2023",
        "contacts": [
            {
                "$oid": "6563e6c1fc13ae0d4c4cd3e3"
            },
            {
                "$oid": "6563e6c1fc13ae0d4c4cd3e4"
            },
            {
                "$oid": "6563e6c1fc13ae0d4c4cd3e5"
            },
            {
                "$oid": "6563e6c1fc13ae0d4c4cd3e6"
            },
            {
                "$oid": "6563e6c1fc13ae0d4c4cd3e7"
            }
        ]
    },
    {
        "id": {
            "$oid": "6563e6c1fc13ae0d4c4cd3e8"
        },
        "username": "Dmitri Coull",
        "password": "uF0,\\s5H>",
        "email": "dcoullh@irs.gov",
        "cellphone": "504-255-5447",
        "address": "088 Trailsway Pass",
        "birthday": "07/28/2023",
        "contacts": [
            {
                "$oid": "6563e6c1fc13ae0d4c4cd3e9"
            },
            {
                "$oid": "6563e6c1fc13ae0d4c4cd3ea"
            },
            {
                "$oid": "6563e6c1fc13ae0d4c4cd3eb"
            },
            {
                "$oid": "6563e6c1fc13ae0d4c4cd3ec"
            },
            {
                "$oid": "6563e6c1fc13ae0d4c4cd3ed"
            }
        ]
    },
    {
        "id": {
            "$oid": "6563e6c1fc13ae0d4c4cd3ee"
        },
        "username": "Cobby Vicker",
        "password": "sJ9&'F)3.E'",
        "email": "cvickeri@yellowpages.com",
        "cellphone": "864-830-7036",
        "address": "13566 Northridge Avenue",
        "birthday": "05/04/2023",
        "contacts": [
            {
                "$oid": "6563e6c1fc13ae0d4c4cd3ef"
            },
            {
                "$oid": "6563e6c1fc13ae0d4c4cd3f0"
            },
            {
                "$oid": "6563e6c1fc13ae0d4c4cd3f1"
            },
            {
                "$oid": "6563e6c1fc13ae0d4c4cd3f2"
            },
            {
                "$oid": "6563e6c1fc13ae0d4c4cd3f3"
            }
        ]
    },
    {
        "id": {
            "$oid": "6563e6c1fc13ae0d4c4cd3f4"
        },
        "username": "Robers Winslett",
        "password": "wJ5?VZC(0",
        "email": "rwinslettj@gnu.org",
        "cellphone": "419-371-5030",
        "address": "413 Tony Lane",
        "birthday": "03/28/2023",
        "contacts": [
            {
                "$oid": "6563e6c1fc13ae0d4c4cd3f5"
            },
            {
                "$oid": "6563e6c1fc13ae0d4c4cd3f6"
            },
            {
                "$oid": "6563e6c1fc13ae0d4c4cd3f7"
            },
            {
                "$oid": "6563e6c1fc13ae0d4c4cd3f8"
            },
            {
                "$oid": "6563e6c1fc13ae0d4c4cd3f9"
            }
        ]
    },
    {
        "id": {
            "$oid": "6563e6c1fc13ae0d4c4cd3fa"
        },
        "username": "Ward Mayow",
        "password": "bO0.=p{7F#&",
        "email": "wmayowk@spotify.com",
        "cellphone": "677-186-5069",
        "address": "39 Randy Avenue",
        "birthday": "09/06/2023",
        "contacts": [
            {
                "$oid": "6563e6c1fc13ae0d4c4cd3fb"
            },
            {
                "$oid": "6563e6c1fc13ae0d4c4cd3fc"
            },
            {
                "$oid": "6563e6c1fc13ae0d4c4cd3fd"
            },
            {
                "$oid": "6563e6c1fc13ae0d4c4cd3fe"
            },
            {
                "$oid": "6563e6c1fc13ae0d4c4cd3ff"
            }
        ]
    },
    {
        "id": {
            "$oid": "6563e6c1fc13ae0d4c4cd400"
        },
        "username": "Chrissy Heam",
        "password": "cH8_(R7UyVlT++YN",
        "email": "cheaml@cbc.ca",
        "cellphone": "361-220-3054",
        "address": "39 Monica Pass",
        "birthday": "02/27/2023",
        "contacts": [
            {
                "$oid": "6563e6c1fc13ae0d4c4cd401"
            },
            {
                "$oid": "6563e6c1fc13ae0d4c4cd402"
            },
            {
                "$oid": "6563e6c1fc13ae0d4c4cd403"
            },
            {
                "$oid": "6563e6c1fc13ae0d4c4cd404"
            },
            {
                "$oid": "6563e6c1fc13ae0d4c4cd405"
            }
        ]
    },
    {
        "id": {
            "$oid": "6563e6c1fc13ae0d4c4cd406"
        },
        "username": "Oren Spillard",
        "password": "kW6}Mi+Pd",
        "email": "ospillardm@amazon.com",
        "cellphone": "497-543-2530",
        "address": "8 Bonner Crossing",
        "birthday": "04/16/2023",
        "contacts": [
            {
                "$oid": "6563e6c1fc13ae0d4c4cd407"
            },
            {
                "$oid": "6563e6c1fc13ae0d4c4cd408"
            },
            {
                "$oid": "6563e6c1fc13ae0d4c4cd409"
            },
            {
                "$oid": "6563e6c1fc13ae0d4c4cd40a"
            },
            {
                "$oid": "6563e6c1fc13ae0d4c4cd40b"
            }
        ]
    },
    {
        "id": {
            "$oid": "6563e6c1fc13ae0d4c4cd40c"
        },
        "username": "Cyndie Wemyss",
        "password": "kR6/y.Nng{'NG",
        "email": "cwemyssn@npr.org",
        "cellphone": "660-591-2469",
        "address": "260 Jenna Terrace",
        "birthday": "07/16/2023",
        "contacts": [
            {
                "$oid": "6563e6c1fc13ae0d4c4cd40d"
            },
            {
                "$oid": "6563e6c1fc13ae0d4c4cd40e"
            },
            {
                "$oid": "6563e6c1fc13ae0d4c4cd40f"
            },
            {
                "$oid": "6563e6c1fc13ae0d4c4cd410"
            },
            {
                "$oid": "6563e6c1fc13ae0d4c4cd411"
            }
        ]
    },
    {
        "id": {
            "$oid": "6563e6c1fc13ae0d4c4cd412"
        },
        "username": "Felice MacFadzean",
        "password": "bL8@N$p>+x",
        "email": "fmacfadzeano@imageshack.us",
        "cellphone": "160-365-3639",
        "address": "702 Buhler Circle",
        "birthday": "03/13/2023",
        "contacts": [
            {
                "$oid": "6563e6c1fc13ae0d4c4cd413"
            },
            {
                "$oid": "6563e6c1fc13ae0d4c4cd414"
            },
            {
                "$oid": "6563e6c1fc13ae0d4c4cd415"
            },
            {
                "$oid": "6563e6c1fc13ae0d4c4cd416"
            },
            {
                "$oid": "6563e6c1fc13ae0d4c4cd417"
            }
        ]
    },
    {
        "id": {
            "$oid": "6563e6c1fc13ae0d4c4cd418"
        },
        "username": "Baudoin Pixton",
        "password": "mU1\"<b(eMJV9",
        "email": "bpixtonp@weebly.com",
        "cellphone": "826-675-6433",
        "address": "87864 Monument Drive",
        "birthday": "03/07/2023",
        "contacts": [
            {
                "$oid": "6563e6c1fc13ae0d4c4cd419"
            },
            {
                "$oid": "6563e6c1fc13ae0d4c4cd41a"
            },
            {
                "$oid": "6563e6c1fc13ae0d4c4cd41b"
            },
            {
                "$oid": "6563e6c1fc13ae0d4c4cd41c"
            },
            {
                "$oid": "6563e6c1fc13ae0d4c4cd41d"
            }
        ]
    },
    {
        "id": {
            "$oid": "6563e6c1fc13ae0d4c4cd41e"
        },
        "username": "Calida Fallens",
        "password": "dJ7\"gsG{T",
        "email": "cfallensq@stanford.edu",
        "cellphone": "773-685-6831",
        "address": "8 Stang Parkway",
        "birthday": "11/04/2023",
        "contacts": [
            {
                "$oid": "6563e6c1fc13ae0d4c4cd41f"
            },
            {
                "$oid": "6563e6c1fc13ae0d4c4cd420"
            },
            {
                "$oid": "6563e6c1fc13ae0d4c4cd421"
            },
            {
                "$oid": "6563e6c1fc13ae0d4c4cd422"
            },
            {
                "$oid": "6563e6c1fc13ae0d4c4cd423"
            }
        ]
    },
    {
        "id": {
            "$oid": "6563e6c1fc13ae0d4c4cd424"
        },
        "username": "Darryl Foran",
        "password": "lD6`ubFzK_",
        "email": "dforanr@elpais.com",
        "cellphone": "320-370-9459",
        "address": "8145 Dryden Way",
        "birthday": "01/06/2023",
        "contacts": [
            {
                "$oid": "6563e6c1fc13ae0d4c4cd425"
            },
            {
                "$oid": "6563e6c1fc13ae0d4c4cd426"
            },
            {
                "$oid": "6563e6c1fc13ae0d4c4cd427"
            },
            {
                "$oid": "6563e6c1fc13ae0d4c4cd428"
            },
            {
                "$oid": "6563e6c1fc13ae0d4c4cd429"
            }
        ]
    },
    {
        "id": {
            "$oid": "6563e6c1fc13ae0d4c4cd42a"
        },
        "username": "Drusi Corrao",
        "password": "iK8?QAO=r&&",
        "email": "dcorraos@livejournal.com",
        "cellphone": "628-308-1171",
        "address": "8181 Troy Junction",
        "birthday": "02/24/2023",
        "contacts": [
            {
                "$oid": "6563e6c1fc13ae0d4c4cd42b"
            },
            {
                "$oid": "6563e6c1fc13ae0d4c4cd42c"
            },
            {
                "$oid": "6563e6c1fc13ae0d4c4cd42d"
            },
            {
                "$oid": "6563e6c1fc13ae0d4c4cd42e"
            },
            {
                "$oid": "6563e6c1fc13ae0d4c4cd42f"
            }
        ]
    },
    {
        "id": {
            "$oid": "6563e6c1fc13ae0d4c4cd430"
        },
        "username": "Marika Daws",
        "password": "pT9?6\\RZ`Y|W./",
        "email": "mdawst@miitbeian.gov.cn",
        "cellphone": "689-500-2504",
        "address": "152 Graedel Lane",
        "birthday": "08/02/2023",
        "contacts": [
            {
                "$oid": "6563e6c1fc13ae0d4c4cd431"
            },
            {
                "$oid": "6563e6c1fc13ae0d4c4cd432"
            },
            {
                "$oid": "6563e6c1fc13ae0d4c4cd433"
            },
            {
                "$oid": "6563e6c1fc13ae0d4c4cd434"
            },
            {
                "$oid": "6563e6c1fc13ae0d4c4cd435"
            }
        ]
    },
    {
        "id": {
            "$oid": "6563e6c1fc13ae0d4c4cd436"
        },
        "username": "Josi Elies",
        "password": "cM1>EmgDNklDu",
        "email": "jeliesu@opera.com",
        "cellphone": "266-474-4444",
        "address": "36802 Buena Vista Avenue",
        "birthday": "12/30/2022",
        "contacts": [
            {
                "$oid": "6563e6c1fc13ae0d4c4cd437"
            },
            {
                "$oid": "6563e6c1fc13ae0d4c4cd438"
            },
            {
                "$oid": "6563e6c1fc13ae0d4c4cd439"
            },
            {
                "$oid": "6563e6c1fc13ae0d4c4cd43a"
            },
            {
                "$oid": "6563e6c1fc13ae0d4c4cd43b"
            }
        ]
    },
    {
        "id": {
            "$oid": "6563e6c1fc13ae0d4c4cd43c"
        },
        "username": "Zacharia McGillivray",
        "password": "wC6.ET4op%NBLJ",
        "email": "zmcgillivrayv@si.edu",
        "cellphone": "266-785-5039",
        "address": "82792 Carberry Terrace",
        "birthday": "03/17/2023",
        "contacts": [
            {
                "$oid": "6563e6c1fc13ae0d4c4cd43d"
            },
            {
                "$oid": "6563e6c1fc13ae0d4c4cd43e"
            },
            {
                "$oid": "6563e6c1fc13ae0d4c4cd43f"
            },
            {
                "$oid": "6563e6c1fc13ae0d4c4cd440"
            },
            {
                "$oid": "6563e6c1fc13ae0d4c4cd441"
            }
        ]
    },
    {
        "id": {
            "$oid": "6563e6c1fc13ae0d4c4cd442"
        },
        "username": "Frannie Jakubowsky",
        "password": "lG8~}B?ZU",
        "email": "fjakubowskyw@ehow.com",
        "cellphone": "154-129-2370",
        "address": "93 American Drive",
        "birthday": "01/23/2023",
        "contacts": [
            {
                "$oid": "6563e6c1fc13ae0d4c4cd443"
            },
            {
                "$oid": "6563e6c1fc13ae0d4c4cd444"
            },
            {
                "$oid": "6563e6c1fc13ae0d4c4cd445"
            },
            {
                "$oid": "6563e6c1fc13ae0d4c4cd446"
            },
            {
                "$oid": "6563e6c1fc13ae0d4c4cd447"
            }
        ]
    },
    {
        "id": {
            "$oid": "6563e6c1fc13ae0d4c4cd448"
        },
        "username": "Crystie Gres",
        "password": "dD7$RFc@J,\"Nk",
        "email": "cgresx@chicagotribune.com",
        "cellphone": "592-154-7530",
        "address": "88 School Drive",
        "birthday": "03/29/2023",
        "contacts": [
            {
                "$oid": "6563e6c1fc13ae0d4c4cd449"
            },
            {
                "$oid": "6563e6c1fc13ae0d4c4cd44a"
            },
            {
                "$oid": "6563e6c1fc13ae0d4c4cd44b"
            },
            {
                "$oid": "6563e6c1fc13ae0d4c4cd44c"
            },
            {
                "$oid": "6563e6c1fc13ae0d4c4cd44d"
            }
        ]
    },
    {
        "id": {
            "$oid": "6563e6c1fc13ae0d4c4cd44e"
        },
        "username": "Orsa Saiens",
        "password": "eF1=G0Ztl",
        "email": "osaiensy@t-online.de",
        "cellphone": "968-413-5608",
        "address": "98 Mockingbird Place",
        "birthday": "04/07/2023",
        "contacts": [
            {
                "$oid": "6563e6c1fc13ae0d4c4cd44f"
            },
            {
                "$oid": "6563e6c1fc13ae0d4c4cd450"
            },
            {
                "$oid": "6563e6c1fc13ae0d4c4cd451"
            },
            {
                "$oid": "6563e6c1fc13ae0d4c4cd452"
            },
            {
                "$oid": "6563e6c1fc13ae0d4c4cd453"
            }
        ]
    },
    {
        "id": {
            "$oid": "6563e6c1fc13ae0d4c4cd454"
        },
        "username": "Colene Morad",
        "password": "gU5/OrX|Uj",
        "email": "cmoradz@so-net.ne.jp",
        "cellphone": "138-376-7301",
        "address": "99 Annamark Center",
        "birthday": "05/04/2023",
        "contacts": [
            {
                "$oid": "6563e6c1fc13ae0d4c4cd455"
            },
            {
                "$oid": "6563e6c1fc13ae0d4c4cd456"
            },
            {
                "$oid": "6563e6c1fc13ae0d4c4cd457"
            },
            {
                "$oid": "6563e6c1fc13ae0d4c4cd458"
            },
            {
                "$oid": "6563e6c1fc13ae0d4c4cd459"
            }
        ]
    },
    {
        "id": {
            "$oid": "6563e6c1fc13ae0d4c4cd45a"
        },
        "username": "Riannon Rivenzon",
        "password": "kB0=a{mS",
        "email": "rrivenzon10@sina.com.cn",
        "cellphone": "446-150-3003",
        "address": "51 Tony Terrace",
        "birthday": "03/16/2023",
        "contacts": [
            {
                "$oid": "6563e6c1fc13ae0d4c4cd45b"
            },
            {
                "$oid": "6563e6c1fc13ae0d4c4cd45c"
            },
            {
                "$oid": "6563e6c1fc13ae0d4c4cd45d"
            },
            {
                "$oid": "6563e6c1fc13ae0d4c4cd45e"
            },
            {
                "$oid": "6563e6c1fc13ae0d4c4cd45f"
            }
        ]
    },
    {
        "id": {
            "$oid": "6563e6c1fc13ae0d4c4cd460"
        },
        "username": "Jedediah Layman",
        "password": "cZ6.hh),ch",
        "email": "jlayman11@istockphoto.com",
        "cellphone": "691-143-8488",
        "address": "445 Lindbergh Street",
        "birthday": "12/09/2022",
        "contacts": [
            {
                "$oid": "6563e6c1fc13ae0d4c4cd461"
            },
            {
                "$oid": "6563e6c1fc13ae0d4c4cd462"
            },
            {
                "$oid": "6563e6c1fc13ae0d4c4cd463"
            },
            {
                "$oid": "6563e6c1fc13ae0d4c4cd464"
            },
            {
                "$oid": "6563e6c1fc13ae0d4c4cd465"
            }
        ]
    },
    {
        "id": {
            "$oid": "6563e6c1fc13ae0d4c4cd466"
        },
        "username": "Birk Risom",
        "password": "pZ3%B_|r",
        "email": "brisom12@smh.com.au",
        "cellphone": "657-679-3055",
        "address": "0537 Dayton Hill",
        "birthday": "09/29/2023",
        "contacts": [
            {
                "$oid": "6563e6c1fc13ae0d4c4cd467"
            },
            {
                "$oid": "6563e6c1fc13ae0d4c4cd468"
            },
            {
                "$oid": "6563e6c1fc13ae0d4c4cd469"
            },
            {
                "$oid": "6563e6c1fc13ae0d4c4cd46a"
            },
            {
                "$oid": "6563e6c1fc13ae0d4c4cd46b"
            }
        ]
    },
    {
        "id": {
            "$oid": "6563e6c1fc13ae0d4c4cd46c"
        },
        "username": "Heywood Lilly",
        "password": "nX0&kY8I>",
        "email": "hlilly13@vk.com",
        "cellphone": "864-865-2919",
        "address": "06697 Hazelcrest Park",
        "birthday": "03/30/2023",
        "contacts": [
            {
                "$oid": "6563e6c1fc13ae0d4c4cd46d"
            },
            {
                "$oid": "6563e6c1fc13ae0d4c4cd46e"
            },
            {
                "$oid": "6563e6c1fc13ae0d4c4cd46f"
            },
            {
                "$oid": "6563e6c1fc13ae0d4c4cd470"
            },
            {
                "$oid": "6563e6c1fc13ae0d4c4cd471"
            }
        ]
    },
    {
        "id": {
            "$oid": "6563e6c1fc13ae0d4c4cd472"
        },
        "username": "Evelyn Cordner",
        "password": "tU8>jF)yFl",
        "email": "ecordner14@ucsd.edu",
        "cellphone": "373-128-8566",
        "address": "2027 Rigney Court",
        "birthday": "06/27/2023",
        "contacts": [
            {
                "$oid": "6563e6c1fc13ae0d4c4cd473"
            },
            {
                "$oid": "6563e6c1fc13ae0d4c4cd474"
            },
            {
                "$oid": "6563e6c1fc13ae0d4c4cd475"
            },
            {
                "$oid": "6563e6c1fc13ae0d4c4cd476"
            },
            {
                "$oid": "6563e6c1fc13ae0d4c4cd477"
            }
        ]
    },
    {
        "id": {
            "$oid": "6563e6c1fc13ae0d4c4cd478"
        },
        "username": "Layne MacNulty",
        "password": "sB1${N'\\dK=",
        "email": "lmacnulty15@slate.com",
        "cellphone": "942-655-2707",
        "address": "274 Parkside Plaza",
        "birthday": "07/25/2023",
        "contacts": [
            {
                "$oid": "6563e6c1fc13ae0d4c4cd479"
            },
            {
                "$oid": "6563e6c1fc13ae0d4c4cd47a"
            },
            {
                "$oid": "6563e6c1fc13ae0d4c4cd47b"
            },
            {
                "$oid": "6563e6c1fc13ae0d4c4cd47c"
            },
            {
                "$oid": "6563e6c1fc13ae0d4c4cd47d"
            }
        ]
    },
    {
        "id": {
            "$oid": "6563e6c1fc13ae0d4c4cd47e"
        },
        "username": "Hoebart Romke",
        "password": "eF6\"5.v6G)8$",
        "email": "hromke16@blogs.com",
        "cellphone": "833-132-0352",
        "address": "5537 Pleasure Road",
        "birthday": "10/15/2023",
        "contacts": [
            {
                "$oid": "6563e6c1fc13ae0d4c4cd47f"
            },
            {
                "$oid": "6563e6c1fc13ae0d4c4cd480"
            },
            {
                "$oid": "6563e6c1fc13ae0d4c4cd481"
            },
            {
                "$oid": "6563e6c1fc13ae0d4c4cd482"
            },
            {
                "$oid": "6563e6c1fc13ae0d4c4cd483"
            }
        ]
    },
    {
        "id": {
            "$oid": "6563e6c1fc13ae0d4c4cd484"
        },
        "username": "Tailor Deighan",
        "password": "mC3{m140|FY",
        "email": "tdeighan17@mail.ru",
        "cellphone": "447-184-4028",
        "address": "031 Carpenter Alley",
        "birthday": "08/06/2023",
        "contacts": [
            {
                "$oid": "6563e6c1fc13ae0d4c4cd485"
            },
            {
                "$oid": "6563e6c1fc13ae0d4c4cd486"
            },
            {
                "$oid": "6563e6c1fc13ae0d4c4cd487"
            },
            {
                "$oid": "6563e6c1fc13ae0d4c4cd488"
            },
            {
                "$oid": "6563e6c1fc13ae0d4c4cd489"
            }
        ]
    },
    {
        "id": {
            "$oid": "6563e6c1fc13ae0d4c4cd48a"
        },
        "username": "Floyd Kovnot",
        "password": "nH9/G)BGIW",
        "email": "fkovnot18@issuu.com",
        "cellphone": "509-948-8161",
        "address": "8 Hanson Alley",
        "birthday": "06/15/2023",
        "contacts": [
            {
                "$oid": "6563e6c1fc13ae0d4c4cd48b"
            },
            {
                "$oid": "6563e6c1fc13ae0d4c4cd48c"
            },
            {
                "$oid": "6563e6c1fc13ae0d4c4cd48d"
            },
            {
                "$oid": "6563e6c1fc13ae0d4c4cd48e"
            },
            {
                "$oid": "6563e6c1fc13ae0d4c4cd48f"
            }
        ]
    },
    {
        "id": {
            "$oid": "6563e6c1fc13ae0d4c4cd490"
        },
        "username": "Rosy Bartoshevich",
        "password": "bS2@wo*y?U}X",
        "email": "rbartoshevich19@youtu.be",
        "cellphone": "827-343-4466",
        "address": "2481 Fieldstone Plaza",
        "birthday": "09/16/2023",
        "contacts": [
            {
                "$oid": "6563e6c1fc13ae0d4c4cd491"
            },
            {
                "$oid": "6563e6c1fc13ae0d4c4cd492"
            },
            {
                "$oid": "6563e6c1fc13ae0d4c4cd493"
            },
            {
                "$oid": "6563e6c1fc13ae0d4c4cd494"
            },
            {
                "$oid": "6563e6c1fc13ae0d4c4cd495"
            }
        ]
    },
    {
        "id": {
            "$oid": "6563e6c1fc13ae0d4c4cd496"
        },
        "username": "Wanids Goodredge",
        "password": "hW7_'hPEo",
        "email": "wgoodredge1a@webs.com",
        "cellphone": "619-105-8219",
        "address": "8 Erie Court",
        "birthday": "04/22/2023",
        "contacts": [
            {
                "$oid": "6563e6c1fc13ae0d4c4cd497"
            },
            {
                "$oid": "6563e6c1fc13ae0d4c4cd498"
            },
            {
                "$oid": "6563e6c1fc13ae0d4c4cd499"
            },
            {
                "$oid": "6563e6c1fc13ae0d4c4cd49a"
            },
            {
                "$oid": "6563e6c1fc13ae0d4c4cd49b"
            }
        ]
    },
    {
        "id": {
            "$oid": "6563e6c1fc13ae0d4c4cd49c"
        },
        "username": "Che Orleton",
        "password": "xP5$f{IJwi20p{hz",
        "email": "corleton1b@indiatimes.com",
        "cellphone": "696-375-2835",
        "address": "42 Lawn Street",
        "birthday": "05/23/2023",
        "contacts": [
            {
                "$oid": "6563e6c1fc13ae0d4c4cd49d"
            },
            {
                "$oid": "6563e6c1fc13ae0d4c4cd49e"
            },
            {
                "$oid": "6563e6c1fc13ae0d4c4cd49f"
            },
            {
                "$oid": "6563e6c1fc13ae0d4c4cd4a0"
            },
            {
                "$oid": "6563e6c1fc13ae0d4c4cd4a1"
            }
        ]
    },
    {
        "id": {
            "$oid": "6563e6c1fc13ae0d4c4cd4a2"
        },
        "username": "Orelia Rattray",
        "password": "wN6/?DIw",
        "email": "orattray1c@addthis.com",
        "cellphone": "637-235-5229",
        "address": "10 Delladonna Trail",
        "birthday": "10/21/2023",
        "contacts": [
            {
                "$oid": "6563e6c1fc13ae0d4c4cd4a3"
            },
            {
                "$oid": "6563e6c1fc13ae0d4c4cd4a4"
            },
            {
                "$oid": "6563e6c1fc13ae0d4c4cd4a5"
            },
            {
                "$oid": "6563e6c1fc13ae0d4c4cd4a6"
            },
            {
                "$oid": "6563e6c1fc13ae0d4c4cd4a7"
            }
        ]
    },
    {
        "id": {
            "$oid": "6563e6c1fc13ae0d4c4cd4a8"
        },
        "username": "Aidan Sustins",
        "password": "uS2%u9.p",
        "email": "asustins1d@paginegialle.it",
        "cellphone": "237-137-9540",
        "address": "97349 Steensland Way",
        "birthday": "07/09/2023",
        "contacts": [
            {
                "$oid": "6563e6c1fc13ae0d4c4cd4a9"
            },
            {
                "$oid": "6563e6c1fc13ae0d4c4cd4aa"
            },
            {
                "$oid": "6563e6c1fc13ae0d4c4cd4ab"
            },
            {
                "$oid": "6563e6c1fc13ae0d4c4cd4ac"
            },
            {
                "$oid": "6563e6c1fc13ae0d4c4cd4ad"
            }
        ]
    },
    {
        "id": {
            "$oid": "6563e6c1fc13ae0d4c4cd4ae"
        },
        "username": "Purcell Ingleson",
        "password": "rP3+({&gu<",
        "email": "pingleson1e@mail.ru",
        "cellphone": "241-593-0616",
        "address": "4 Mandrake Terrace",
        "birthday": "03/27/2023",
        "contacts": [
            {
                "$oid": "6563e6c1fc13ae0d4c4cd4af"
            },
            {
                "$oid": "6563e6c1fc13ae0d4c4cd4b0"
            },
            {
                "$oid": "6563e6c1fc13ae0d4c4cd4b1"
            },
            {
                "$oid": "6563e6c1fc13ae0d4c4cd4b2"
            },
            {
                "$oid": "6563e6c1fc13ae0d4c4cd4b3"
            }
        ]
    },
    {
        "id": {
            "$oid": "6563e6c1fc13ae0d4c4cd4b4"
        },
        "username": "Sherwin Pringle",
        "password": "hK8/~1Wz6%\"l=G`",
        "email": "springle1f@usnews.com",
        "cellphone": "217-695-5215",
        "address": "7 Carpenter Way",
        "birthday": "09/14/2023",
        "contacts": [
            {
                "$oid": "6563e6c1fc13ae0d4c4cd4b5"
            },
            {
                "$oid": "6563e6c1fc13ae0d4c4cd4b6"
            },
            {
                "$oid": "6563e6c1fc13ae0d4c4cd4b7"
            },
            {
                "$oid": "6563e6c1fc13ae0d4c4cd4b8"
            },
            {
                "$oid": "6563e6c1fc13ae0d4c4cd4b9"
            }
        ]
    },
    {
        "id": {
            "$oid": "6563e6c1fc13ae0d4c4cd4ba"
        },
        "username": "Malcolm Dolman",
        "password": "nX0%vZU`J%1P<V#",
        "email": "mdolman1g@delicious.com",
        "cellphone": "836-363-5297",
        "address": "11731 Nevada Street",
        "birthday": "08/08/2023",
        "contacts": [
            {
                "$oid": "6563e6c1fc13ae0d4c4cd4bb"
            },
            {
                "$oid": "6563e6c1fc13ae0d4c4cd4bc"
            },
            {
                "$oid": "6563e6c1fc13ae0d4c4cd4bd"
            },
            {
                "$oid": "6563e6c1fc13ae0d4c4cd4be"
            },
            {
                "$oid": "6563e6c1fc13ae0d4c4cd4bf"
            }
        ]
    },
    {
        "id": {
            "$oid": "6563e6c1fc13ae0d4c4cd4c0"
        },
        "username": "Aleta Lapish",
        "password": "aR6%)KnQ",
        "email": "alapish1h@miibeian.gov.cn",
        "cellphone": "916-140-6605",
        "address": "476 Mosinee Parkway",
        "birthday": "08/29/2023",
        "contacts": [
            {
                "$oid": "6563e6c1fc13ae0d4c4cd4c1"
            },
            {
                "$oid": "6563e6c1fc13ae0d4c4cd4c2"
            },
            {
                "$oid": "6563e6c1fc13ae0d4c4cd4c3"
            },
            {
                "$oid": "6563e6c1fc13ae0d4c4cd4c4"
            },
            {
                "$oid": "6563e6c1fc13ae0d4c4cd4c5"
            }
        ]
    },
    {
        "id": {
            "$oid": "6563e6c1fc13ae0d4c4cd4c6"
        },
        "username": "Jermaine Illidge",
        "password": "qO7,CAWTzgP?f,",
        "email": "jillidge1i@vkontakte.ru",
        "cellphone": "483-707-0031",
        "address": "967 Gale Pass",
        "birthday": "03/23/2023",
        "contacts": [
            {
                "$oid": "6563e6c1fc13ae0d4c4cd4c7"
            },
            {
                "$oid": "6563e6c1fc13ae0d4c4cd4c8"
            },
            {
                "$oid": "6563e6c1fc13ae0d4c4cd4c9"
            },
            {
                "$oid": "6563e6c1fc13ae0d4c4cd4ca"
            },
            {
                "$oid": "6563e6c1fc13ae0d4c4cd4cb"
            }
        ]
    },
    {
        "id": {
            "$oid": "6563e6c1fc13ae0d4c4cd4cc"
        },
        "username": "Thaddeus Hucklesby",
        "password": "oA1#hOwl%e*}BO",
        "email": "thucklesby1j@aboutads.info",
        "cellphone": "186-127-3725",
        "address": "6233 Melby Lane",
        "birthday": "09/23/2023",
        "contacts": [
            {
                "$oid": "6563e6c1fc13ae0d4c4cd4cd"
            },
            {
                "$oid": "6563e6c1fc13ae0d4c4cd4ce"
            },
            {
                "$oid": "6563e6c1fc13ae0d4c4cd4cf"
            },
            {
                "$oid": "6563e6c1fc13ae0d4c4cd4d0"
            },
            {
                "$oid": "6563e6c1fc13ae0d4c4cd4d1"
            }
        ]
    },
    {
        "id": {
            "$oid": "6563e6c1fc13ae0d4c4cd4d2"
        },
        "username": "Shanon Cammack",
        "password": "rM5/Lk>Zp",
        "email": "scammack1k@wp.com",
        "cellphone": "498-547-8859",
        "address": "300 Coleman Avenue",
        "birthday": "05/21/2023",
        "contacts": [
            {
                "$oid": "6563e6c1fc13ae0d4c4cd4d3"
            },
            {
                "$oid": "6563e6c1fc13ae0d4c4cd4d4"
            },
            {
                "$oid": "6563e6c1fc13ae0d4c4cd4d5"
            },
            {
                "$oid": "6563e6c1fc13ae0d4c4cd4d6"
            },
            {
                "$oid": "6563e6c1fc13ae0d4c4cd4d7"
            }
        ]
    },
    {
        "id": {
            "$oid": "6563e6c1fc13ae0d4c4cd4d8"
        },
        "username": "Alwyn Aizikovitch",
        "password": "aG4%K1Uj`ciTf#OX",
        "email": "aaizikovitch1l@moonfruit.com",
        "cellphone": "747-525-4607",
        "address": "035 Erie Street",
        "birthday": "05/18/2023",
        "contacts": [
            {
                "$oid": "6563e6c1fc13ae0d4c4cd4d9"
            },
            {
                "$oid": "6563e6c1fc13ae0d4c4cd4da"
            },
            {
                "$oid": "6563e6c1fc13ae0d4c4cd4db"
            },
            {
                "$oid": "6563e6c1fc13ae0d4c4cd4dc"
            },
            {
                "$oid": "6563e6c1fc13ae0d4c4cd4dd"
            }
        ]
    },
    {
        "id": {
            "$oid": "6563e6c1fc13ae0d4c4cd4de"
        },
        "username": "Bancroft Pendered",
        "password": "pC2}ZC?Z",
        "email": "bpendered1m@oaic.gov.au",
        "cellphone": "257-986-0531",
        "address": "1 Mitchell Lane",
        "birthday": "03/31/2023",
        "contacts": [
            {
                "$oid": "6563e6c1fc13ae0d4c4cd4df"
            },
            {
                "$oid": "6563e6c1fc13ae0d4c4cd4e0"
            },
            {
                "$oid": "6563e6c1fc13ae0d4c4cd4e1"
            },
            {
                "$oid": "6563e6c1fc13ae0d4c4cd4e2"
            },
            {
                "$oid": "6563e6c1fc13ae0d4c4cd4e3"
            }
        ]
    },
    {
        "id": {
            "$oid": "6563e6c1fc13ae0d4c4cd4e4"
        },
        "username": "Dino De Beauchamp",
        "password": "vL5+6RDqJo965%c",
        "email": "dde1n@mozilla.org",
        "cellphone": "164-385-7462",
        "address": "225 Hermina Park",
        "birthday": "07/27/2023",
        "contacts": [
            {
                "$oid": "6563e6c1fc13ae0d4c4cd4e5"
            },
            {
                "$oid": "6563e6c1fc13ae0d4c4cd4e6"
            },
            {
                "$oid": "6563e6c1fc13ae0d4c4cd4e7"
            },
            {
                "$oid": "6563e6c1fc13ae0d4c4cd4e8"
            },
            {
                "$oid": "6563e6c1fc13ae0d4c4cd4e9"
            }
        ]
    },
    {
        "id": {
            "$oid": "6563e6c1fc13ae0d4c4cd4ea"
        },
        "username": "Ailyn Fenlon",
        "password": "jV3%*QR(\\IB,SR",
        "email": "afenlon1o@desdev.cn",
        "cellphone": "761-383-6760",
        "address": "82012 Blue Bill Park Street",
        "birthday": "05/11/2023",
        "contacts": [
            {
                "$oid": "6563e6c1fc13ae0d4c4cd4eb"
            },
            {
                "$oid": "6563e6c1fc13ae0d4c4cd4ec"
            },
            {
                "$oid": "6563e6c1fc13ae0d4c4cd4ed"
            },
            {
                "$oid": "6563e6c1fc13ae0d4c4cd4ee"
            },
            {
                "$oid": "6563e6c1fc13ae0d4c4cd4ef"
            }
        ]
    },
    {
        "id": {
            "$oid": "6563e6c1fc13ae0d4c4cd4f0"
        },
        "username": "Lexis Leemans",
        "password": "tE2`?t8}",
        "email": "lleemans1p@omniture.com",
        "cellphone": "260-725-5821",
        "address": "1 Dakota Hill",
        "birthday": "06/30/2023",
        "contacts": [
            {
                "$oid": "6563e6c1fc13ae0d4c4cd4f1"
            },
            {
                "$oid": "6563e6c1fc13ae0d4c4cd4f2"
            },
            {
                "$oid": "6563e6c1fc13ae0d4c4cd4f3"
            },
            {
                "$oid": "6563e6c1fc13ae0d4c4cd4f4"
            },
            {
                "$oid": "6563e6c1fc13ae0d4c4cd4f5"
            }
        ]
    },
    {
        "id": {
            "$oid": "6563e6c1fc13ae0d4c4cd4f6"
        },
        "username": "Darlleen Rittmeyer",
        "password": "yW1#>'%L",
        "email": "drittmeyer1q@alexa.com",
        "cellphone": "439-634-4487",
        "address": "25 Lakewood Parkway",
        "birthday": "10/27/2023",
        "contacts": [
            {
                "$oid": "6563e6c1fc13ae0d4c4cd4f7"
            },
            {
                "$oid": "6563e6c1fc13ae0d4c4cd4f8"
            },
            {
                "$oid": "6563e6c1fc13ae0d4c4cd4f9"
            },
            {
                "$oid": "6563e6c1fc13ae0d4c4cd4fa"
            },
            {
                "$oid": "6563e6c1fc13ae0d4c4cd4fb"
            }
        ]
    },
    {
        "id": {
            "$oid": "6563e6c1fc13ae0d4c4cd4fc"
        },
        "username": "Feliks Chretien",
        "password": "lI6'7@M*mC)zj\"l0",
        "email": "fchretien1r@springer.com",
        "cellphone": "222-947-0420",
        "address": "08 Muir Drive",
        "birthday": "07/08/2023",
        "contacts": [
            {
                "$oid": "6563e6c1fc13ae0d4c4cd4fd"
            },
            {
                "$oid": "6563e6c1fc13ae0d4c4cd4fe"
            },
            {
                "$oid": "6563e6c1fc13ae0d4c4cd4ff"
            },
            {
                "$oid": "6563e6c1fc13ae0d4c4cd500"
            },
            {
                "$oid": "6563e6c1fc13ae0d4c4cd501"
            }
        ]
    },
    {
        "id": {
            "$oid": "6563e6c1fc13ae0d4c4cd502"
        },
        "username": "Opaline Kemmet",
        "password": "yB1`2J3iMD&F~",
        "email": "okemmet1s@imgur.com",
        "cellphone": "248-600-6135",
        "address": "981 Starling Hill",
        "birthday": "05/28/2023",
        "contacts": [
            {
                "$oid": "6563e6c1fc13ae0d4c4cd503"
            },
            {
                "$oid": "6563e6c1fc13ae0d4c4cd504"
            },
            {
                "$oid": "6563e6c1fc13ae0d4c4cd505"
            },
            {
                "$oid": "6563e6c1fc13ae0d4c4cd506"
            },
            {
                "$oid": "6563e6c1fc13ae0d4c4cd507"
            }
        ]
    },
    {
        "id": {
            "$oid": "6563e6c1fc13ae0d4c4cd508"
        },
        "username": "Rriocard O'Rourke",
        "password": "vO3>9{yY*g2",
        "email": "rorourke1t@sourceforge.net",
        "cellphone": "495-970-7361",
        "address": "66345 Clyde Gallagher Place",
        "birthday": "03/29/2023",
        "contacts": [
            {
                "$oid": "6563e6c1fc13ae0d4c4cd509"
            },
            {
                "$oid": "6563e6c1fc13ae0d4c4cd50a"
            },
            {
                "$oid": "6563e6c1fc13ae0d4c4cd50b"
            },
            {
                "$oid": "6563e6c1fc13ae0d4c4cd50c"
            },
            {
                "$oid": "6563e6c1fc13ae0d4c4cd50d"
            }
        ]
    },
    {
        "id": {
            "$oid": "6563e6c1fc13ae0d4c4cd50e"
        },
        "username": "Aindrea Berndsen",
        "password": "tC0$rn!q5fS2*",
        "email": "aberndsen1u@hud.gov",
        "cellphone": "862-880-5870",
        "address": "6 Mariners Cove Circle",
        "birthday": "04/20/2023",
        "contacts": [
            {
                "$oid": "6563e6c1fc13ae0d4c4cd50f"
            },
            {
                "$oid": "6563e6c1fc13ae0d4c4cd510"
            },
            {
                "$oid": "6563e6c1fc13ae0d4c4cd511"
            },
            {
                "$oid": "6563e6c1fc13ae0d4c4cd512"
            },
            {
                "$oid": "6563e6c1fc13ae0d4c4cd513"
            }
        ]
    },
    {
        "id": {
            "$oid": "6563e6c1fc13ae0d4c4cd514"
        },
        "username": "Gussy Fitt",
        "password": "lN5<le7B",
        "email": "gfitt1v@princeton.edu",
        "cellphone": "546-404-0194",
        "address": "1 Claremont Place",
        "birthday": "05/16/2023",
        "contacts": [
            {
                "$oid": "6563e6c1fc13ae0d4c4cd515"
            },
            {
                "$oid": "6563e6c1fc13ae0d4c4cd516"
            },
            {
                "$oid": "6563e6c1fc13ae0d4c4cd517"
            },
            {
                "$oid": "6563e6c1fc13ae0d4c4cd518"
            },
            {
                "$oid": "6563e6c1fc13ae0d4c4cd519"
            }
        ]
    },
    {
        "id": {
            "$oid": "6563e6c1fc13ae0d4c4cd51a"
        },
        "username": "Talya Kleyn",
        "password": "yR9!9TzPog",
        "email": "tkleyn1w@mayoclinic.com",
        "cellphone": "661-802-1422",
        "address": "8 Schlimgen Lane",
        "birthday": "05/13/2023",
        "contacts": [
            {
                "$oid": "6563e6c1fc13ae0d4c4cd51b"
            },
            {
                "$oid": "6563e6c1fc13ae0d4c4cd51c"
            },
            {
                "$oid": "6563e6c1fc13ae0d4c4cd51d"
            },
            {
                "$oid": "6563e6c1fc13ae0d4c4cd51e"
            },
            {
                "$oid": "6563e6c1fc13ae0d4c4cd51f"
            }
        ]
    },
    {
        "id": {
            "$oid": "6563e6c1fc13ae0d4c4cd520"
        },
        "username": "Terrance Klehn",
        "password": "zF2@4J{xF,d6",
        "email": "tklehn1x@nifty.com",
        "cellphone": "506-733-8426",
        "address": "935 Coleman Way",
        "birthday": "07/04/2023",
        "contacts": [
            {
                "$oid": "6563e6c1fc13ae0d4c4cd521"
            },
            {
                "$oid": "6563e6c1fc13ae0d4c4cd522"
            },
            {
                "$oid": "6563e6c1fc13ae0d4c4cd523"
            },
            {
                "$oid": "6563e6c1fc13ae0d4c4cd524"
            },
            {
                "$oid": "6563e6c1fc13ae0d4c4cd525"
            }
        ]
    },
    {
        "id": {
            "$oid": "6563e6c1fc13ae0d4c4cd526"
        },
        "username": "Luz Frascone",
        "password": "pY7\\HKsy/03@6",
        "email": "lfrascone1y@walmart.com",
        "cellphone": "995-267-0744",
        "address": "067 Kipling Circle",
        "birthday": "03/26/2023",
        "contacts": [
            {
                "$oid": "6563e6c1fc13ae0d4c4cd527"
            },
            {
                "$oid": "6563e6c1fc13ae0d4c4cd528"
            },
            {
                "$oid": "6563e6c1fc13ae0d4c4cd529"
            },
            {
                "$oid": "6563e6c1fc13ae0d4c4cd52a"
            },
            {
                "$oid": "6563e6c1fc13ae0d4c4cd52b"
            }
        ]
    },
    {
        "id": {
            "$oid": "6563e6c1fc13ae0d4c4cd52c"
        },
        "username": "Casie Kett",
        "password": "rG5=b&c)3bBFgS",
        "email": "ckett1z@zdnet.com",
        "cellphone": "830-126-2251",
        "address": "0 Hermina Point",
        "birthday": "04/17/2023",
        "contacts": [
            {
                "$oid": "6563e6c1fc13ae0d4c4cd52d"
            },
            {
                "$oid": "6563e6c1fc13ae0d4c4cd52e"
            },
            {
                "$oid": "6563e6c1fc13ae0d4c4cd52f"
            },
            {
                "$oid": "6563e6c1fc13ae0d4c4cd530"
            },
            {
                "$oid": "6563e6c1fc13ae0d4c4cd531"
            }
        ]
    },
    {
        "id": {
            "$oid": "6563e6c1fc13ae0d4c4cd532"
        },
        "username": "Olivie Pepperell",
        "password": "yX5\"mQ$XcYasi*+O",
        "email": "opepperell20@etsy.com",
        "cellphone": "224-414-6568",
        "address": "807 Cordelia Place",
        "birthday": "05/25/2023",
        "contacts": [
            {
                "$oid": "6563e6c1fc13ae0d4c4cd533"
            },
            {
                "$oid": "6563e6c1fc13ae0d4c4cd534"
            },
            {
                "$oid": "6563e6c1fc13ae0d4c4cd535"
            },
            {
                "$oid": "6563e6c1fc13ae0d4c4cd536"
            },
            {
                "$oid": "6563e6c1fc13ae0d4c4cd537"
            }
        ]
    },
    {
        "id": {
            "$oid": "6563e6c1fc13ae0d4c4cd538"
        },
        "username": "Aloise Gaine",
        "password": "kQ6_5%Gh6\\R`",
        "email": "againe21@webs.com",
        "cellphone": "220-214-4565",
        "address": "893 Spaight Place",
        "birthday": "05/01/2023",
        "contacts": [
            {
                "$oid": "6563e6c1fc13ae0d4c4cd539"
            },
            {
                "$oid": "6563e6c1fc13ae0d4c4cd53a"
            },
            {
                "$oid": "6563e6c1fc13ae0d4c4cd53b"
            },
            {
                "$oid": "6563e6c1fc13ae0d4c4cd53c"
            },
            {
                "$oid": "6563e6c1fc13ae0d4c4cd53d"
            }
        ]
    },
    {
        "id": {
            "$oid": "6563e6c1fc13ae0d4c4cd53e"
        },
        "username": "Hebert Antonazzi",
        "password": "dS9})h{'8",
        "email": "hantonazzi22@samsung.com",
        "cellphone": "441-354-6822",
        "address": "532 Mockingbird Park",
        "birthday": "05/01/2023",
        "contacts": [
            {
                "$oid": "6563e6c1fc13ae0d4c4cd53f"
            },
            {
                "$oid": "6563e6c1fc13ae0d4c4cd540"
            },
            {
                "$oid": "6563e6c1fc13ae0d4c4cd541"
            },
            {
                "$oid": "6563e6c1fc13ae0d4c4cd542"
            },
            {
                "$oid": "6563e6c1fc13ae0d4c4cd543"
            }
        ]
    },
    {
        "id": {
            "$oid": "6563e6c1fc13ae0d4c4cd544"
        },
        "username": "Keen Truggian",
        "password": "hV3|wEgz,*Jl5",
        "email": "ktruggian23@ebay.co.uk",
        "cellphone": "311-688-4267",
        "address": "0 Maple Wood Hill",
        "birthday": "11/03/2023",
        "contacts": [
            {
                "$oid": "6563e6c1fc13ae0d4c4cd545"
            },
            {
                "$oid": "6563e6c1fc13ae0d4c4cd546"
            },
            {
                "$oid": "6563e6c1fc13ae0d4c4cd547"
            },
            {
                "$oid": "6563e6c1fc13ae0d4c4cd548"
            },
            {
                "$oid": "6563e6c1fc13ae0d4c4cd549"
            }
        ]
    },
    {
        "id": {
            "$oid": "6563e6c1fc13ae0d4c4cd54a"
        },
        "username": "Sergent Splaven",
        "password": "aK5'@6YX{_8`By{s",
        "email": "ssplaven24@reference.com",
        "cellphone": "768-470-1738",
        "address": "34 Bowman Court",
        "birthday": "01/13/2023",
        "contacts": [
            {
                "$oid": "6563e6c1fc13ae0d4c4cd54b"
            },
            {
                "$oid": "6563e6c1fc13ae0d4c4cd54c"
            },
            {
                "$oid": "6563e6c1fc13ae0d4c4cd54d"
            },
            {
                "$oid": "6563e6c1fc13ae0d4c4cd54e"
            },
            {
                "$oid": "6563e6c1fc13ae0d4c4cd54f"
            }
        ]
    },
    {
        "id": {
            "$oid": "6563e6c1fc13ae0d4c4cd550"
        },
        "username": "Tanya Lockhead",
        "password": "wO5+#*I0",
        "email": "tlockhead25@mapy.cz",
        "cellphone": "647-383-6310",
        "address": "184 Graedel Crossing",
        "birthday": "03/08/2023",
        "contacts": [
            {
                "$oid": "6563e6c1fc13ae0d4c4cd551"
            },
            {
                "$oid": "6563e6c1fc13ae0d4c4cd552"
            },
            {
                "$oid": "6563e6c1fc13ae0d4c4cd553"
            },
            {
                "$oid": "6563e6c1fc13ae0d4c4cd554"
            },
            {
                "$oid": "6563e6c1fc13ae0d4c4cd555"
            }
        ]
    },
    {
        "id": {
            "$oid": "6563e6c1fc13ae0d4c4cd556"
        },
        "username": "Clayson Warn",
        "password": "nB4@l*wAY>8jtE}",
        "email": "cwarn26@dmoz.org",
        "cellphone": "984-894-1499",
        "address": "67162 Thierer Trail",
        "birthday": "07/11/2023",
        "contacts": [
            {
                "$oid": "6563e6c1fc13ae0d4c4cd557"
            },
            {
                "$oid": "6563e6c1fc13ae0d4c4cd558"
            },
            {
                "$oid": "6563e6c1fc13ae0d4c4cd559"
            },
            {
                "$oid": "6563e6c1fc13ae0d4c4cd55a"
            },
            {
                "$oid": "6563e6c1fc13ae0d4c4cd55b"
            }
        ]
    },
    {
        "id": {
            "$oid": "6563e6c1fc13ae0d4c4cd55c"
        },
        "username": "Michelina Glencross",
        "password": "fT1*t%AU\\B8",
        "email": "mglencross27@umn.edu",
        "cellphone": "929-591-5486",
        "address": "314 Jenifer Road",
        "birthday": "09/12/2023",
        "contacts": [
            {
                "$oid": "6563e6c1fc13ae0d4c4cd55d"
            },
            {
                "$oid": "6563e6c1fc13ae0d4c4cd55e"
            },
            {
                "$oid": "6563e6c1fc13ae0d4c4cd55f"
            },
            {
                "$oid": "6563e6c1fc13ae0d4c4cd560"
            },
            {
                "$oid": "6563e6c1fc13ae0d4c4cd561"
            }
        ]
    },
    {
        "id": {
            "$oid": "6563e6c1fc13ae0d4c4cd562"
        },
        "username": "Bendicty Justice",
        "password": "aT4{t!~d?h+Y327c",
        "email": "bjustice28@weebly.com",
        "cellphone": "103-291-4473",
        "address": "936 Lake View Parkway",
        "birthday": "04/14/2023",
        "contacts": [
            {
                "$oid": "6563e6c1fc13ae0d4c4cd563"
            },
            {
                "$oid": "6563e6c1fc13ae0d4c4cd564"
            },
            {
                "$oid": "6563e6c1fc13ae0d4c4cd565"
            },
            {
                "$oid": "6563e6c1fc13ae0d4c4cd566"
            },
            {
                "$oid": "6563e6c1fc13ae0d4c4cd567"
            }
        ]
    },
    {
        "id": {
            "$oid": "6563e6c1fc13ae0d4c4cd568"
        },
        "username": "Estele Mingo",
        "password": "bY0{l79lj",
        "email": "emingo29@typepad.com",
        "cellphone": "838-632-7512",
        "address": "1002 Barby Court",
        "birthday": "10/28/2023",
        "contacts": [
            {
                "$oid": "6563e6c1fc13ae0d4c4cd569"
            },
            {
                "$oid": "6563e6c1fc13ae0d4c4cd56a"
            },
            {
                "$oid": "6563e6c1fc13ae0d4c4cd56b"
            },
            {
                "$oid": "6563e6c1fc13ae0d4c4cd56c"
            },
            {
                "$oid": "6563e6c1fc13ae0d4c4cd56d"
            }
        ]
    },
    {
        "id": {
            "$oid": "6563e6c1fc13ae0d4c4cd56e"
        },
        "username": "Papagena Elsom",
        "password": "pZ4@Z(JR67WFEQt",
        "email": "pelsom2a@telegraph.co.uk",
        "cellphone": "802-317-8125",
        "address": "2 Monica Terrace",
        "birthday": "05/23/2023",
        "contacts": [
            {
                "$oid": "6563e6c1fc13ae0d4c4cd56f"
            },
            {
                "$oid": "6563e6c1fc13ae0d4c4cd570"
            },
            {
                "$oid": "6563e6c1fc13ae0d4c4cd571"
            },
            {
                "$oid": "6563e6c1fc13ae0d4c4cd572"
            },
            {
                "$oid": "6563e6c1fc13ae0d4c4cd573"
            }
        ]
    },
    {
        "id": {
            "$oid": "6563e6c1fc13ae0d4c4cd574"
        },
        "username": "Cass Shurmore",
        "password": "lA7#Rd`Uy",
        "email": "cshurmore2b@mediafire.com",
        "cellphone": "636-376-6503",
        "address": "26 Caliangt Parkway",
        "birthday": "05/02/2023",
        "contacts": [
            {
                "$oid": "6563e6c1fc13ae0d4c4cd575"
            },
            {
                "$oid": "6563e6c1fc13ae0d4c4cd576"
            },
            {
                "$oid": "6563e6c1fc13ae0d4c4cd577"
            },
            {
                "$oid": "6563e6c1fc13ae0d4c4cd578"
            },
            {
                "$oid": "6563e6c1fc13ae0d4c4cd579"
            }
        ]
    },
    {
        "id": {
            "$oid": "6563e6c1fc13ae0d4c4cd57a"
        },
        "username": "Sherie Jorat",
        "password": "lW7|P|`+Kg\"@c+",
        "email": "sjorat2c@alexa.com",
        "cellphone": "294-632-3456",
        "address": "7659 Dexter Junction",
        "birthday": "09/01/2023",
        "contacts": [
            {
                "$oid": "6563e6c1fc13ae0d4c4cd57b"
            },
            {
                "$oid": "6563e6c1fc13ae0d4c4cd57c"
            },
            {
                "$oid": "6563e6c1fc13ae0d4c4cd57d"
            },
            {
                "$oid": "6563e6c1fc13ae0d4c4cd57e"
            },
            {
                "$oid": "6563e6c1fc13ae0d4c4cd57f"
            }
        ]
    },
    {
        "id": {
            "$oid": "6563e6c1fc13ae0d4c4cd580"
        },
        "username": "Lolly Rosebotham",
        "password": "kX2\\{chNYHK",
        "email": "lrosebotham2d@newyorker.com",
        "cellphone": "165-125-4728",
        "address": "01410 Rutledge Road",
        "birthday": "06/21/2023",
        "contacts": [
            {
                "$oid": "6563e6c1fc13ae0d4c4cd581"
            },
            {
                "$oid": "6563e6c1fc13ae0d4c4cd582"
            },
            {
                "$oid": "6563e6c1fc13ae0d4c4cd583"
            },
            {
                "$oid": "6563e6c1fc13ae0d4c4cd584"
            },
            {
                "$oid": "6563e6c1fc13ae0d4c4cd585"
            }
        ]
    },
    {
        "id": {
            "$oid": "6563e6c1fc13ae0d4c4cd586"
        },
        "username": "Trix MacKissack",
        "password": "oX0~vDxqZXEm",
        "email": "tmackissack2e@bloglines.com",
        "cellphone": "325-488-6254",
        "address": "35 Melrose Hill",
        "birthday": "03/09/2023",
        "contacts": [
            {
                "$oid": "6563e6c1fc13ae0d4c4cd587"
            },
            {
                "$oid": "6563e6c1fc13ae0d4c4cd588"
            },
            {
                "$oid": "6563e6c1fc13ae0d4c4cd589"
            },
            {
                "$oid": "6563e6c1fc13ae0d4c4cd58a"
            },
            {
                "$oid": "6563e6c1fc13ae0d4c4cd58b"
            }
        ]
    },
    {
        "id": {
            "$oid": "6563e6c1fc13ae0d4c4cd58c"
        },
        "username": "Maressa Headly",
        "password": "gC6!Q`Vpf}",
        "email": "mheadly2f@phpbb.com",
        "cellphone": "137-415-6050",
        "address": "954 Farmco Drive",
        "birthday": "10/26/2023",
        "contacts": [
            {
                "$oid": "6563e6c1fc13ae0d4c4cd58d"
            },
            {
                "$oid": "6563e6c1fc13ae0d4c4cd58e"
            },
            {
                "$oid": "6563e6c1fc13ae0d4c4cd58f"
            },
            {
                "$oid": "6563e6c1fc13ae0d4c4cd590"
            },
            {
                "$oid": "6563e6c1fc13ae0d4c4cd591"
            }
        ]
    },
    {
        "id": {
            "$oid": "6563e6c1fc13ae0d4c4cd592"
        },
        "username": "Anna Derrell",
        "password": "wX9+ILJ_\\?A",
        "email": "aderrell2g@1688.com",
        "cellphone": "737-164-6291",
        "address": "7364 Eggendart Plaza",
        "birthday": "09/16/2023",
        "contacts": [
            {
                "$oid": "6563e6c1fc13ae0d4c4cd593"
            },
            {
                "$oid": "6563e6c1fc13ae0d4c4cd594"
            },
            {
                "$oid": "6563e6c1fc13ae0d4c4cd595"
            },
            {
                "$oid": "6563e6c1fc13ae0d4c4cd596"
            },
            {
                "$oid": "6563e6c1fc13ae0d4c4cd597"
            }
        ]
    },
    {
        "id": {
            "$oid": "6563e6c1fc13ae0d4c4cd598"
        },
        "username": "Marybelle Fyers",
        "password": "eR0$s'.BZ*y",
        "email": "mfyers2h@unesco.org",
        "cellphone": "121-631-0792",
        "address": "7 Sheridan Alley",
        "birthday": "07/05/2023",
        "contacts": [
            {
                "$oid": "6563e6c1fc13ae0d4c4cd599"
            },
            {
                "$oid": "6563e6c1fc13ae0d4c4cd59a"
            },
            {
                "$oid": "6563e6c1fc13ae0d4c4cd59b"
            },
            {
                "$oid": "6563e6c1fc13ae0d4c4cd59c"
            },
            {
                "$oid": "6563e6c1fc13ae0d4c4cd59d"
            }
        ]
    },
    {
        "id": {
            "$oid": "6563e6c1fc13ae0d4c4cd59e"
        },
        "username": "Izaak Rafferty",
        "password": "zP2|\"K\"t$uNpE?G",
        "email": "irafferty2i@topsy.com",
        "cellphone": "659-965-6712",
        "address": "0324 Monica Hill",
        "birthday": "03/25/2023",
        "contacts": [
            {
                "$oid": "6563e6c1fc13ae0d4c4cd59f"
            },
            {
                "$oid": "6563e6c1fc13ae0d4c4cd5a0"
            },
            {
                "$oid": "6563e6c1fc13ae0d4c4cd5a1"
            },
            {
                "$oid": "6563e6c1fc13ae0d4c4cd5a2"
            },
            {
                "$oid": "6563e6c1fc13ae0d4c4cd5a3"
            }
        ]
    },
    {
        "id": {
            "$oid": "6563e6c1fc13ae0d4c4cd5a4"
        },
        "username": "Luke Staddom",
        "password": "sF9.Q>T(S4%",
        "email": "lstaddom2j@4shared.com",
        "cellphone": "175-353-4595",
        "address": "10571 Wayridge Center",
        "birthday": "10/26/2023",
        "contacts": [
            {
                "$oid": "6563e6c1fc13ae0d4c4cd5a5"
            },
            {
                "$oid": "6563e6c1fc13ae0d4c4cd5a6"
            },
            {
                "$oid": "6563e6c1fc13ae0d4c4cd5a7"
            },
            {
                "$oid": "6563e6c1fc13ae0d4c4cd5a8"
            },
            {
                "$oid": "6563e6c1fc13ae0d4c4cd5a9"
            }
        ]
    },
    {
        "id": {
            "$oid": "6563e6c1fc13ae0d4c4cd5aa"
        },
        "username": "Walden Kneafsey",
        "password": "dE9%sQo9NSX",
        "email": "wkneafsey2k@umich.edu",
        "cellphone": "465-422-1673",
        "address": "6935 Warner Crossing",
        "birthday": "10/04/2023",
        "contacts": [
            {
                "$oid": "6563e6c1fc13ae0d4c4cd5ab"
            },
            {
                "$oid": "6563e6c1fc13ae0d4c4cd5ac"
            },
            {
                "$oid": "6563e6c1fc13ae0d4c4cd5ad"
            },
            {
                "$oid": "6563e6c1fc13ae0d4c4cd5ae"
            },
            {
                "$oid": "6563e6c1fc13ae0d4c4cd5af"
            }
        ]
    },
    {
        "id": {
            "$oid": "6563e6c1fc13ae0d4c4cd5b0"
        },
        "username": "Austen Tooth",
        "password": "yT5?SX9+j",
        "email": "atooth2l@tamu.edu",
        "cellphone": "605-708-3536",
        "address": "84666 Sutherland Road",
        "birthday": "05/01/2023",
        "contacts": [
            {
                "$oid": "6563e6c1fc13ae0d4c4cd5b1"
            },
            {
                "$oid": "6563e6c1fc13ae0d4c4cd5b2"
            },
            {
                "$oid": "6563e6c1fc13ae0d4c4cd5b3"
            },
            {
                "$oid": "6563e6c1fc13ae0d4c4cd5b4"
            },
            {
                "$oid": "6563e6c1fc13ae0d4c4cd5b5"
            }
        ]
    },
    {
        "id": {
            "$oid": "6563e6c1fc13ae0d4c4cd5b6"
        },
        "username": "Abie Boffin",
        "password": "qC0\\o9F.n\\#w1",
        "email": "aboffin2m@tiny.cc",
        "cellphone": "291-364-3646",
        "address": "6 Forest Avenue",
        "birthday": "06/20/2023",
        "contacts": [
            {
                "$oid": "6563e6c1fc13ae0d4c4cd5b7"
            },
            {
                "$oid": "6563e6c1fc13ae0d4c4cd5b8"
            },
            {
                "$oid": "6563e6c1fc13ae0d4c4cd5b9"
            },
            {
                "$oid": "6563e6c1fc13ae0d4c4cd5ba"
            },
            {
                "$oid": "6563e6c1fc13ae0d4c4cd5bb"
            }
        ]
    },
    {
        "id": {
            "$oid": "6563e6c1fc13ae0d4c4cd5bc"
        },
        "username": "Westley Ivanilov",
        "password": "zC6'MzxfT*ak,X0",
        "email": "wivanilov2n@ustream.tv",
        "cellphone": "157-307-0145",
        "address": "18 Bellgrove Way",
        "birthday": "06/05/2023",
        "contacts": [
            {
                "$oid": "6563e6c1fc13ae0d4c4cd5bd"
            },
            {
                "$oid": "6563e6c1fc13ae0d4c4cd5be"
            },
            {
                "$oid": "6563e6c1fc13ae0d4c4cd5bf"
            },
            {
                "$oid": "6563e6c1fc13ae0d4c4cd5c0"
            },
            {
                "$oid": "6563e6c1fc13ae0d4c4cd5c1"
            }
        ]
    },
    {
        "id": {
            "$oid": "6563e6c1fc13ae0d4c4cd5c2"
        },
        "username": "George Bernt",
        "password": "dP4'.Xhi?U",
        "email": "gbernt2o@163.com",
        "cellphone": "468-880-7166",
        "address": "745 American Ash Alley",
        "birthday": "05/31/2023",
        "contacts": [
            {
                "$oid": "6563e6c1fc13ae0d4c4cd5c3"
            },
            {
                "$oid": "6563e6c1fc13ae0d4c4cd5c4"
            },
            {
                "$oid": "6563e6c1fc13ae0d4c4cd5c5"
            },
            {
                "$oid": "6563e6c1fc13ae0d4c4cd5c6"
            },
            {
                "$oid": "6563e6c1fc13ae0d4c4cd5c7"
            }
        ]
    },
    {
        "id": {
            "$oid": "6563e6c1fc13ae0d4c4cd5c8"
        },
        "username": "Griffin Beaston",
        "password": "oF0.mx9lrySl",
        "email": "gbeaston2p@usatoday.com",
        "cellphone": "134-519-3333",
        "address": "007 Dayton Avenue",
        "birthday": "03/13/2023",
        "contacts": [
            {
                "$oid": "6563e6c1fc13ae0d4c4cd5c9"
            },
            {
                "$oid": "6563e6c1fc13ae0d4c4cd5ca"
            },
            {
                "$oid": "6563e6c1fc13ae0d4c4cd5cb"
            },
            {
                "$oid": "6563e6c1fc13ae0d4c4cd5cc"
            },
            {
                "$oid": "6563e6c1fc13ae0d4c4cd5cd"
            }
        ]
    },
    {
        "id": {
            "$oid": "6563e6c1fc13ae0d4c4cd5ce"
        },
        "username": "Bartholomew Everall",
        "password": "qR1(}HL0",
        "email": "beverall2q@netscape.com",
        "cellphone": "250-700-3531",
        "address": "0638 Shoshone Crossing",
        "birthday": "06/10/2023",
        "contacts": [
            {
                "$oid": "6563e6c1fc13ae0d4c4cd5cf"
            },
            {
                "$oid": "6563e6c1fc13ae0d4c4cd5d0"
            },
            {
                "$oid": "6563e6c1fc13ae0d4c4cd5d1"
            },
            {
                "$oid": "6563e6c1fc13ae0d4c4cd5d2"
            },
            {
                "$oid": "6563e6c1fc13ae0d4c4cd5d3"
            }
        ]
    },
    {
        "id": {
            "$oid": "6563e6c1fc13ae0d4c4cd5d4"
        },
        "username": "Caye Sclater",
        "password": "dP5&&Sno9Ff_D*",
        "email": "csclater2r@mozilla.com",
        "cellphone": "812-200-0738",
        "address": "9 Hauk Place",
        "birthday": "11/23/2023",
        "contacts": [
            {
                "$oid": "6563e6c1fc13ae0d4c4cd5d5"
            },
            {
                "$oid": "6563e6c1fc13ae0d4c4cd5d6"
            },
            {
                "$oid": "6563e6c1fc13ae0d4c4cd5d7"
            },
            {
                "$oid": "6563e6c1fc13ae0d4c4cd5d8"
            },
            {
                "$oid": "6563e6c1fc13ae0d4c4cd5d9"
            }
        ]
    }
]